setup.py
thriftr/__init__.py
thriftr/lexer.py
thriftr/model.py
thriftr/parser.py
thriftr.egg-info/PKG-INFO
thriftr.egg-info/SOURCES.txt
thriftr.egg-info/dependency_links.txt
thriftr.egg-info/not-zip-safe
thriftr.egg-info/requires.txt
thriftr.egg-info/top_level.txt