Metadata-Version: 1.1
Name: thriftr
Version: 0.0.1
Summary: Pure python apache thrift parser
Home-page: https://github.com/hit9/thriftr.git
Author: hit9
Author-email: nz2324@126.com
License: MIT
Platform: UNKNOWN
Classifier: Topic :: Software Development
Classifier: Development Status :: 2 - Pre-Alpha
Classifier: Intended Audience :: Developers
Classifier: License :: OSI Approved :: MIT License
Classifier: Programming Language :: Python :: 2.7
Classifier: Programming Language :: Python :: 3.3
Classifier: Programming Language :: Python :: 3.4
Classifier: Programming Language :: Python :: Implementation :: CPython
Classifier: Programming Language :: Python :: Implementation :: PyPy
